piximind/__init__.py
piximind/princo.py
piximind-2.2.5.dist-info/LICENSE.txt
piximind-2.2.5.dist-info/METADATA
piximind-2.2.5.dist-info/WHEEL
piximind-2.2.5.dist-info/top_level.txt
piximind-2.2.5.dist-info/RECORD
