Metadata-Version: 2.1
Name: piximind
Version: 2.2.5
Summary: princo package
Author: mahdi sahnoun
License-File: LICENSE.txt
